exonware/xdata/__init__.py
exonware_xdata-0.0.1.dist-info/METADATA
exonware_xdata-0.0.1.dist-info/WHEEL
exonware_xdata-0.0.1.dist-info/licenses/LICENSE
exonware_xdata-0.0.1.dist-info/RECORD
